nonebot_plugin_mcmod/__init__.py
nonebot_plugin_mcmod/forward_msg.py
nonebot_plugin_mcmod/get_source.py
nonebot_plugin_mcmod/mcmod.py
nonebot_plugin_mcmod-1.3.6.dist-info/METADATA
nonebot_plugin_mcmod-1.3.6.dist-info/WHEEL
nonebot_plugin_mcmod-1.3.6.dist-info/RECORD
