Metadata-Version: 2.3
Name: nonebot-plugin-mcmod
Version: 1.3.6
Summary: 通过 https://www.mcmod.cn 获取模组、整合包、教程等信息。
License: MIT
Author: chrysoljq
Author-email: study@iqach.top
Requires-Python: >=3.9,<4.0
Classifier: License :: OSI Approved :: MIT License
Classifier: Programming Language :: Python :: 3
Classifier: Programming Language :: Python :: 3.9
Classifier: Programming Language :: Python :: 3.10
Classifier: Programming Language :: Python :: 3.11
Classifier: Programming Language :: Python :: 3.12
Classifier: Programming Language :: Python :: 3.13
Provides-Extra: dev
Requires-Dist: aiohttp (>=3.11.0)
Requires-Dist: beautifulsoup4 (>=4.12.0)
Requires-Dist: nonebot-adapter-onebot (>=2.0.0)
Requires-Dist: nonebot2 (>=2.3.0)
Project-URL: Homepage, https://github.com/chrysoljq/nonebot-plugin-mcmod
Project-URL: Repository, https://github.com/chrysoljq/nonebot-plugin-mcmod
